setup.cfg
setup.py
django_rescuests.egg-info/PKG-INFO
django_rescuests.egg-info/SOURCES.txt
django_rescuests.egg-info/dependency_links.txt
django_rescuests.egg-info/pbr.json
django_rescuests.egg-info/top_level.txt
rescuests/__init__.py
rescuests/admin.py
rescuests/cron.py
rescuests/models.py
rescuests/signals.py
rescuests/migrations/0001_initial.py
rescuests/migrations/__init__.py