Metadata-Version: 1.1
Name: django-rescuests
Version: 0.2.3
Summary: A framework sending, tracking and retrying REST requests in Django.
Home-page: https://github.com/BloodyD/django_rescuests
Author: Dimitri Korsch
Author-email: korschdima@gmail.com
License: LICENSE
Keywords: requests,fault tollerant,django,framework
Platform: UNKNOWN
Classifier: Development Status :: 4 - Beta
Classifier: Environment :: Web Environment
Classifier: Framework :: Django
Classifier: Intended Audience :: Developers
Classifier: Programming Language :: Python
Classifier: License :: OSI Approved :: Apache Software License
Classifier: License :: OSI Approved :: BSD License
Classifier: Operating System :: OS Independent
Classifier: Topic :: Software Development
Requires: django (>=1.6)
Requires: django_cron
